fcl/__init__.py
fcl/collision_data.py
fcl/fcl.cpp
fcl/fcl.cpython-314-x86_64-linux-gnu.so
fcl/fcl.pyx
fcl/fcl_defs.pxd
fcl/octomap_defs.pxd
fcl/std_defs.pxd
fcl/version.py
python_fcl.libs/libccd-894a431f.so.2.0
python_fcl.libs/libfcl-9f362718.so.0.7.0
python_fcl.libs/liboctomap-18b406fe.so.1.9.8
python_fcl.libs/liboctomath-7b3fdef0.so.1.9.8
python_fcl-0.7.0.10.dist-info/METADATA
python_fcl-0.7.0.10.dist-info/WHEEL
python_fcl-0.7.0.10.dist-info/top_level.txt
python_fcl-0.7.0.10.dist-info/RECORD
python_fcl-0.7.0.10.dist-info/licenses/LICENSE
