Metadata-Version: 2.4
Name: python-fcl
Version: 0.7.0.10
Summary: Python bindings for the Flexible Collision Library
Author: Michael Dawson-Haggerty, See contributor list
Author-email: Jelle Feringa <jelleferinga@gmail.com>, Matthew Matl <mmatl@eecs.berkeley.edu>, Shirokuma <rootstock_acg@yahoo.co.jp>
Maintainer-email: Matthew Matl <mmatl@eecs.berkeley.edu>
License: BSD
Project-URL: Homepage, https://github.com/berkeleyautomation/python-fcl
Keywords: fcl collision distance
Classifier: Development Status :: 3 - Alpha
Classifier: License :: OSI Approved :: BSD License
Classifier: Operating System :: POSIX :: Linux
Classifier: Operating System :: MacOS
Classifier: Operating System :: Microsoft :: Windows
Classifier: Programming Language :: Python :: 3
Classifier: Programming Language :: Python :: 3.7
Classifier: Programming Language :: Python :: 3.8
Classifier: Programming Language :: Python :: 3.9
Classifier: Programming Language :: Python :: 3.10
Classifier: Programming Language :: Python :: 3.11
Classifier: Programming Language :: Python :: 3.12
Classifier: Programming Language :: Python :: Implementation :: CPython
Requires-Python: >=3.9
License-File: LICENSE
Requires-Dist: numpy; python_version < "3.12"
Requires-Dist: numpy>=1.26.0b1; python_version >= "3.12"
Requires-Dist: Cython
Dynamic: license-file
